_libparse.cpython-311-darwin.so
libparse-0.3.1.dist-info/RECORD
libparse-0.3.1.dist-info/WHEEL
libparse-0.3.1.dist-info/top_level.txt
libparse-0.3.1.dist-info/METADATA
libparse/__init__.py
libparse/__version__.py
libparse/libparse.py
