Metadata-Version: 2.1
Name: libparse
Version: 0.3.1
Summary: Python wrapper around Yosys' libparse module
Author: Efabless Corporation and Contributors
Author-email: donn@efabless.com
Classifier: License :: OSI Approved :: Apache Software License
Classifier: Programming Language :: Python :: 3
Classifier: Intended Audience :: Developers
Classifier: Operating System :: POSIX :: Linux
Classifier: Operating System :: MacOS :: MacOS X
Requires-Python: >3.6
Requires-Dist: wheel
